pygray_snap/933c6bfbdec03c6332fe.wasm
pygray_snap/__init__.py
pygray_snap/core.cp39-win_amd64.pyd
pygray_snap/core.pyi
pygray_snap/pycore.py
pygray_snap/ua.jsonl
pygray_snap/utils.py
pygray_snap-0.1.dist-info/METADATA
pygray_snap-0.1.dist-info/WHEEL
pygray_snap-0.1.dist-info/top_level.txt
pygray_snap-0.1.dist-info/RECORD
